MANIFEST.in
README.md
setup.cfg
setup.py
onigmo/onigmo.py
onigmo/testpy.py
onigmo/.libs/libonigmo.6.dylib
onigmo/.libs/libonigmo.dylib
py_onigmo.egg-info/PKG-INFO
py_onigmo.egg-info/SOURCES.txt
py_onigmo.egg-info/dependency_links.txt
py_onigmo.egg-info/top_level.txt