Metadata-Version: 2.1
Name: py-onigmo
Version: 6.2.0
Summary: Provide onigmo regexp support
Home-page: https://github.com/scodeman/py-onigmo
Author: Scodeman
Author-email: scodeman@scode.io
License: UNKNOWN
Keywords: onigmo,regular expression
Platform: UNKNOWN
Classifier: License :: OSI Approved :: MIT License
Classifier: Programming Language :: Python :: 3
Classifier: Operating System :: OS Independent
